LICENSE
MANIFEST.in
README.md
setup.cfg
setup.py
trex_lib.egg-info/PKG-INFO
trex_lib.egg-info/SOURCES.txt
trex_lib.egg-info/dependency_links.txt
trex_lib.egg-info/requires.txt
trex_lib.egg-info/top_level.txt
trexlib/__init__.py
trexlib/conf_to_remove.py
trexlib/forms/__init__.py
trexlib/forms/base_forms.py
trexlib/forms/common/__init__.py
trexlib/forms/common/common_forms.py
trexlib/libs/__init__.py
trexlib/libs/controllers/__init__.py
trexlib/libs/controllers/task_base_routes.py
trexlib/libs/facebook/__init__.py
trexlib/libs/facebook/util/__init__.py
trexlib/libs/facebook/util/whatsapp_util.py
trexlib/libs/firebase/__init__.py
trexlib/libs/firebase/firebase_helper.py
trexlib/libs/flask_wtf/__init__.py
trexlib/libs/flask_wtf/crsf_ext.py
trexlib/libs/flask_wtf/request_wrapper.py
trexlib/libs/wtforms/__init__.py
trexlib/libs/wtforms/fields.py
trexlib/libs/wtforms/validators.py
trexlib/tools/__init__.py
trexlib/tools/generate_captcha_image.py
trexlib/utils/__init__.py
trexlib/utils/crypto_util.py
trexlib/utils/log_util.py
trexlib/utils/member_card_generator.py
trexlib/utils/security_util.py
trexlib/utils/sms_util.py
trexlib/utils/string_util.py
trexlib/utils/url_util.py
trexlib/utils/common/__init__.py
trexlib/utils/common/cache_util.py
trexlib/utils/common/common_util.py
trexlib/utils/common/config_util.py
trexlib/utils/common/conftest.py
trexlib/utils/common/crm_util.py
trexlib/utils/common/currency_util.py
trexlib/utils/common/date_util.py
trexlib/utils/common/float_util.py
trexlib/utils/common/format_util.py
trexlib/utils/common/language_util.py
trexlib/utils/common/pagination_util.py
trexlib/utils/common/phone_util.py
trexlib/utils/common/user_util.py
trexlib/utils/google/__init__.py
trexlib/utils/google/bigquery_util.py
trexlib/utils/google/cloud_tasks_util.py
trexlib/utils/google/gcloud_util.py