Metadata-Version: 2.4
Name: trex_lib
Version: 1.7.2
Summary: TRex Core library package
Home-page: https://bitbucket.org/lokjac/trex-lib
Author: Jack Lok
Author-email: sglok77@gmail.com
Classifier: Programming Language :: Python :: 3
Classifier: License :: OSI Approved :: MIT License
Classifier: Operating System :: OS Independent
License-File: LICENSE
Requires-Dist: python-dateutil
Requires-Dist: cryptography
Requires-Dist: urllib3
Requires-Dist: phonenumbers
Requires-Dist: email_validator
Requires-Dist: Flask-Script
Requires-Dist: basicauth
Dynamic: author
Dynamic: author-email
Dynamic: classifier
Dynamic: description
Dynamic: description-content-type
Dynamic: home-page
Dynamic: license-file
Dynamic: requires-dist
Dynamic: summary
